systemdynamics/__init__.py
systemdynamics/cld.py
systemdynamics/plots.py
systemdynamics/sdm.py
systemdynamics-0.1.5.dist-info/LICENSE
systemdynamics-0.1.5.dist-info/METADATA
systemdynamics-0.1.5.dist-info/WHEEL
systemdynamics-0.1.5.dist-info/top_level.txt
systemdynamics-0.1.5.dist-info/RECORD
