Metadata-Version: 2.1
Name: systemdynamics
Version: 0.1.5
License-File: LICENSE
Requires-Dist: pandas >=1.3.0
Requires-Dist: openpyxl >=3.1.0
Requires-Dist: seaborn >=0.11.0
Requires-Dist: xlsxwriter >=3.0.5
Requires-Dist: scipy
Requires-Dist: tqdm
Requires-Dist: sympy
Requires-Dist: networkx
Requires-Dist: networkx >=2.5
Requires-Dist: ipywidgets
Requires-Dist: numexpr >=2.8.4
Requires-Dist: bottleneck >=1.3.6
Requires-Dist: tabulate >=0.8.9
